README.rst
setup.py
Qsim/ion_chain/__init__.py
Qsim/ion_chain/ion_system.py
Qsim/ion_chain/eigendiagram/exci_diagram.py
Qsim/ion_chain/eigendiagram/init__.py
Qsim/ion_chain/interaction/__init__.py
Qsim/ion_chain/interaction/pure_spin.py
Qsim/ion_chain/interaction/spin_phonon.py
Qsim/ion_chain/ising/__init__.py
Qsim/ion_chain/ising/ising_c.py
Qsim/ion_chain/ising/ising_ps.py
Qsim/ion_chain/transfer/__init__.py
Qsim/ion_chain/transfer/anharmonic_transfer - 副本.py
Qsim/ion_chain/transfer/anharmonic_transfer.py
Qsim/ion_chain/transfer/chaos.py
Qsim/ion_chain/transfer/elec_transfer.py
Qsim/ion_chain/transfer/exci_operators.py
Qsim/ion_chain/transfer/exci_transfer.py
Qsim/ion_chain/transfer/multi_core.py
Qsim/operator/__init__.py
Qsim/operator/phonon.py
Qsim/operator/spin.py
Qsim_trapped_ions.egg-info/PKG-INFO
Qsim_trapped_ions.egg-info/SOURCES.txt
Qsim_trapped_ions.egg-info/dependency_links.txt
Qsim_trapped_ions.egg-info/requires.txt
Qsim_trapped_ions.egg-info/top_level.txt
test/test.py