Metadata-Version: 2.1
Name: Qsim-trapped-ions
Version: 1.0.5
Summary: Numerical simulation of trapped ion quantum dynamics
Home-page: https://github.com/TrappedIonRice/Open-Quantum-system-simulation
Author: Mingjian Zhu
Author-email: mz40@rice.edu
